debdialer/__init__.py
debdialer/__main__.py
debdialer/config.json
debdialer/design.py
debdialer/dialer_main.py
debdialer/dialercli_main.py
debdialer/fetch_details.py
debdialer/kdeconnect_utils.py
debdialer/utils.py
debdialer/resources/DialerCodes.json
debdialer/resources/flags/AD-32.png
debdialer/resources/flags/AE-32.png
debdialer/resources/flags/AF-32.png
debdialer/resources/flags/AG-32.png
debdialer/resources/flags/AI-32.png
debdialer/resources/flags/AL-32.png
debdialer/resources/flags/AM-32.png
debdialer/resources/flags/AO-32.png
debdialer/resources/flags/AQ-32.png
debdialer/resources/flags/AR-32.png
debdialer/resources/flags/AS-32.png
debdialer/resources/flags/AT-32.png
debdialer/resources/flags/AU-32.png
debdialer/resources/flags/AW-32.png
debdialer/resources/flags/AX-32.png
debdialer/resources/flags/AZ-32.png
debdialer/resources/flags/BA-32.png
debdialer/resources/flags/BB-32.png
debdialer/resources/flags/BD-32.png
debdialer/resources/flags/BE-32.png
debdialer/resources/flags/BF-32.png
debdialer/resources/flags/BG-32.png
debdialer/resources/flags/BH-32.png
debdialer/resources/flags/BI-32.png
debdialer/resources/flags/BJ-32.png
debdialer/resources/flags/BL-32.png
debdialer/resources/flags/BM-32.png
debdialer/resources/flags/BN-32.png
debdialer/resources/flags/BO-32.png
debdialer/resources/flags/BQ-32.png
debdialer/resources/flags/BR-32.png
debdialer/resources/flags/BS-32.png
debdialer/resources/flags/BT-32.png
debdialer/resources/flags/BV-32.png
debdialer/resources/flags/BW-32.png
debdialer/resources/flags/BY-32.png
debdialer/resources/flags/BZ-32.png
debdialer/resources/flags/CA-32.png
debdialer/resources/flags/CC-32.png
debdialer/resources/flags/CD-32.png
debdialer/resources/flags/CF-32.png
debdialer/resources/flags/CG-32.png
debdialer/resources/flags/CH-32.png
debdialer/resources/flags/CI-32.png
debdialer/resources/flags/CK-32.png
debdialer/resources/flags/CL-32.png
debdialer-0.26.dist-info/METADATA
debdialer-0.26.dist-info/RECORD
debdialer-0.26.dist-info/WHEEL
debdialer-0.26.dist-info/entry_points.txt
debdialer-0.26.dist-info/top_level.txt
