Metadata-Version: 2.1
Name: debdialer
Version: 0.26
Summary: Click-to-dial pop-up window.
Home-page: https://salsa.debian.org/comfortablydumb-guest/debdialer
Author: Vishal Gupta
Author-email: vishalg8897@gmail.com
License: GNU
Platform: UNKNOWN
Classifier: License :: OSI Approved :: GNU Affero General Public License v3
Classifier: Natural Language :: English
Classifier: Operating System :: POSIX :: Linux
Classifier: Programming Language :: Python :: 3.0
Classifier: Programming Language :: Python :: 3.1
Classifier: Programming Language :: Python :: 3.2
Classifier: Programming Language :: Python :: 3.3
Classifier: Programming Language :: Python :: 3.4
Classifier: Programming Language :: Python :: 3.5
Classifier: Programming Language :: Python :: 3.6
Classifier: Programming Language :: Python :: 3 :: Only
Classifier: Topic :: Communications :: Telephony
Classifier: Topic :: Communications :: Internet Phone
Classifier: Topic :: Utilities
Requires-Dist: pytz
Requires-Dist: phonenumbers
Requires-Dist: vobject
